__init__.py
pathtemplate.py
pathtemplate-0.1.2.dist-info/METADATA
pathtemplate-0.1.2.dist-info/WHEEL
pathtemplate-0.1.2.dist-info/top_level.txt
pathtemplate-0.1.2.dist-info/RECORD
