Metadata-Version: 2.1
Name: pathtemplate
Version: 0.1.2
Summary: create paths with formatted placeholders
Author-email: Wojtek Baginski <wobagi@gmail.com>
License: MIT
Requires-Python: >=3.11
